lightning_nets/__init__.py
lightning_nets/gan.py
lightning_nets/data/__init__.py
lightning_nets/data/mnist_data_module.py
lightning_nets/data/torch_dataset.py
lightning_nets/hooks/__init__.py
lightning_nets/hooks/callbacks.py
lightning_nets/hooks/plotters/__init__.py
lightning_nets/hooks/plotters/data_plotter.py
lightning_nets/hooks/plotters/line_chart_data_plotter.py
lightning_nets/hooks/plotters/mnist_data_plotter.py
lightning_nets/models/__init__.py
lightning_nets/models/networks/__init__.py
lightning_nets/models/networks/networks_1d.py
lightning_nets/models/networks/networks_2d.py
lightning_nets/modules/__init__.py
lightning_nets/modules/basic_nn_module.py
lightning_nets/modules/boundary_equilibrium_gan_module.py
lightning_nets/modules/vanilla_gan_module.py
lightning_nets/modules/wasserstein_gan_gp_module.py
lightning_nets-0.0.0.96.dist-info/LICENSE
lightning_nets-0.0.0.96.dist-info/METADATA
lightning_nets-0.0.0.96.dist-info/WHEEL
lightning_nets-0.0.0.96.dist-info/top_level.txt
lightning_nets-0.0.0.96.dist-info/RECORD
